cli.py
main.py
bato_downloader-6.0.0.dist-info/licenses/LICENSE
gui/__init__.py
gui/main_window.py
gui/styles.py
gui/workers.py
gui/widgets/__init__.py
gui/widgets/download_widget.py
gui/widgets/manga_widget.py
gui/widgets/search_widget.py
gui/widgets/settings_widget.py
src/__init__.py
src/config.py
src/logger.py
src/downloader/__init__.py
src/downloader/chapter_downloader.py
src/downloader/converter.py
src/downloader/image_downloader.py
src/scraper/__init__.py
src/scraper/chapters.py
src/scraper/images.py
src/scraper/info.py
src/scraper/search.py
bato_downloader-6.0.0.dist-info/METADATA
bato_downloader-6.0.0.dist-info/WHEEL
bato_downloader-6.0.0.dist-info/entry_points.txt
bato_downloader-6.0.0.dist-info/top_level.txt
bato_downloader-6.0.0.dist-info/RECORD
