Metadata-Version: 2.4
Name: bato-downloader
Version: 6.0.0
Summary: A beautiful manga downloader for Bato.to with PyQt6 GUI and Rich CLI
Author-email: Yui007 <akrtrt782@gmail.com>
License: MIT
Project-URL: Homepage, https://github.com/Yui007/bato_downloader
Project-URL: Repository, https://github.com/Yui007/bato_downloader
Project-URL: Issues, https://github.com/Yui007/bato_downloader/issues
Keywords: manga,downloader,bato,batoto,comic,webtoon
Classifier: Development Status :: 5 - Production/Stable
Classifier: Environment :: Console
Classifier: Environment :: X11 Applications :: Qt
Classifier: Intended Audience :: End Users/Desktop
Classifier: Programming Language :: Python :: 3
Classifier: Programming Language :: Python :: 3.8
Classifier: Programming Language :: Python :: 3.9
Classifier: Programming Language :: Python :: 3.10
Classifier: Programming Language :: Python :: 3.11
Classifier: Programming Language :: Python :: 3.12
Classifier: License :: OSI Approved :: MIT License
Classifier: Operating System :: OS Independent
Classifier: Topic :: Internet :: WWW/HTTP
Classifier: Topic :: Multimedia :: Graphics
Requires-Python: >=3.8
License-File: LICENSE
Requires-Dist: PyQt6>=6.0.0
Requires-Dist: typer>=0.9.0
Requires-Dist: rich>=13.0.0
Requires-Dist: requests>=2.28.0
Requires-Dist: Pillow>=9.0.0
Provides-Extra: dev
Requires-Dist: pyinstaller; extra == "dev"
Requires-Dist: build; extra == "dev"
Requires-Dist: twine; extra == "dev"
Dynamic: license-file
